coden/__init__.py
coden-0.6.dist-info/LICENSE.txt
coden-0.6.dist-info/METADATA
coden-0.6.dist-info/WHEEL
coden-0.6.dist-info/top_level.txt
coden-0.6.dist-info/RECORD
