Metadata-Version: 2.1
Name: coden
Version: 0.6
Summary: Has functions on topic "codes"
Home-page: https://github.com/Tams-Tams/Codes/tree/master/coden_0.6.git
Author: Tanmay Earappa
Author-email: Tams.Mathe@gmail.com
License: MIT
Platform: UNKNOWN
Classifier: Programming Language :: Python :: 3
Classifier: License :: OSI Approved :: MIT License
Classifier: Operating System :: OS Independent
